{
  "version": "v5",
  "title": "V5 鋼之帝國 關卡",
  "note": "三輪各 10 關；第 F 關為最終關卡。",
  "rounds": [
    {
      "id": 1,
      "label": "第一輪",
      "enemies": [
        [3, "疫苗種", 10, "11121", "-", "網路空間"],
        [4, "資料種", 15, "11211", "-", null],
        [12, "病毒種", 40, "11121", "-", null],
        [9, "資料種", 44, "12111", "-", null],
        [18, "資料種", 84, "11211", "-", "盒子藝術"],
        [17, "資料種", 96, "11221", "-", null],
        [27, "疫苗種", 140, "21121", "-", null],
        [26, "病毒種", 150, "12222", "命中 -0", null],
        [13, "病毒種", 60, "22222", "命中 -20", null],
        [29, "病毒種", 165, "11222", "命中 -10", "神秘區域"]
      ]
    },
    {
      "id": 2,
      "label": "第二輪",
      "enemies": [
        [4, "資料種", 15, "12111", "-", null],
        [8, "疫苗種", 32, "11121", "-", null],
        [7, "疫苗種", 48, "12121", "-", null],
        [11, "病毒種", 50, "11121", "-", null],
        [20, "病毒種", 88, "11221", "-", null],
        [15, "疫苗種", 100, "12121", "-", null],
        [24, "資料種", 145, "21211", "-", null],
        [25, "病毒種", 170, "21212", "命中 -5", null],
        [22, "病毒種", 110, "12222", "命中 -18", null],
        [25, "病毒種", 170, "21212", "命中 -10", null]
      ]
    },
    {
      "id": 3,
      "label": "第三輪",
      "enemies": [
        [5, "病毒種", 18, "12111", "-", null],
        [10, "資料種", 36, "11121", "-", null],
        [7, "疫苗種", 48, "12121", "-", null],
        [16, "疫苗種", 80, "12121", "-", null],
        [21, "疫苗種", 92, "21121", "-", null],
        [15, "疫苗種", 100, "12121", "-", null],
        [24, "資料種", 145, "21211", "-", null],
        [28, "自由種", 165, "21222", "命中 -10", null],
        [32, "病毒種", 180, "22222", "命中 -10", null],
        [31, "病毒種", 205, "12222", "命中 -10", null]
      ]
    }
  ]
}
